{
  "@context": {
    "wine_label": "ark:/87287/d7794w/schema#",
    "rdfs": "http://www.w3.org/2000/01/rdf-schema#",
    "ucdlib": "http://schema.library.ucdavis.edu/schema#",
    "xsd": "http://www.w3.org/2001/XMLSchema#",
    "schema": "http://schema.org/"
  },
  "@id": "",
  "@type": [
    "ucdlib:WineLabel",
    "schema:VisualArtwork",
    "schema:CreativeWork",
    "http://fedora.info/definitions/v4/repository#ArchivalGroup"
  ],
  "schema:about": {
    "@id": "http://id.worldcat.org/fast/1204565"
  },
  "schema:identifier": [
    "ark:/85140/d4759k"
  ],
  "schema:inLanguage": "it-IT",
  "schema:keywords": "Italy",
  "schema:license": {
    "@id": "http://rightsstatements.org/vocab/CNE/1.0/"
  },
  "schema:name": "Lodovico e Piero Antinori. (ALP) Cantine dei Marchesi ยง Old Red Chianti Wine ยง Florence; Italy",
  "schema:publisher": {
    "@id": "http://id.loc.gov/authorities/names/no2008108707",
    "schema:name": "University of California, Davis. General Library. Dept. of Special Collections"
  },
  "wine_label:city_region": "Florence; Italy",
  "wine_label:date": "1931",
  "wine_label:digitization_number": "0101/",
  "wine_label:folder": "Still--Italy",
  "wine_label:marginalia": "\"At home. November, 1940.  .50.\" \"Italy (Red)\"",
  "wine_label:producer": "Lodovico e Piero Antinori. (ALP) Cantine dei Marchesi",
  "wine_label:wine_type": "Old Red Chianti Wine"
}
